{
  "$schema": "https://json.schemastore.org/tsconfig",
  "extends": "./base.json",
  "compilerOptions": {
    "lib": ["ES2022"],
    "target": "ES2022",
    "module": "ESNext",
    "moduleResolution": "Bundler",
    "jsx": "react-native",

    "allowJs": true,
    "noEmit": true,
    "skipLibCheck": true,
    "resolveJsonModule": true,
    "allowSyntheticDefaultImports": true,
    "esModuleInterop": true,

    "strict": true,
    "forceConsistentCasingInFileNames": true,
    "isolatedModules": true,

    "baseUrl": ".",
    "paths": { "@/*": ["./src/*"] },

    "types": ["react", "react-dom", "node"]
  },
  "include": ["**/*.ts", "**/*.tsx", "**/*.js", "**/*.jsx", "expo-env.d.ts"],
  "exclude": ["node_modules", "babel.config.js", "metro.config.js", "jest.config.js", ".expo", "dist", "build", "web-build"]
}
